climax/__init__.py
climax-0.5.0.dist-info/LICENSE
climax-0.5.0.dist-info/METADATA
climax-0.5.0.dist-info/WHEEL
climax-0.5.0.dist-info/top_level.txt
climax-0.5.0.dist-info/RECORD
